dbt_ensure_tag.py
dbt_ensure_tag-0.0.3.dist-info/LICENSE
dbt_ensure_tag-0.0.3.dist-info/METADATA
dbt_ensure_tag-0.0.3.dist-info/WHEEL
dbt_ensure_tag-0.0.3.dist-info/entry_points.txt
dbt_ensure_tag-0.0.3.dist-info/top_level.txt
dbt_ensure_tag-0.0.3.dist-info/RECORD
