Metadata-Version: 2.1
Name: dbt-ensure-tag
Version: 0.0.3
Summary: checks dbt models for tags
Home-page: https://github.com/j-clemons/dbt-ensure-tag
Author: Jonathan Clemons
Author-email: j-clemons@tuta.io
License: MIT
Classifier: License :: OSI Approved :: MIT License
Classifier: Programming Language :: Python :: 3
Classifier: Programming Language :: Python :: 3 :: Only
Requires-Python: >=3.8
License-File: LICENSE
Requires-Dist: dbt-core (>=1.5.0)
